pyvispoly-0.3.1.dist-info/WHEEL
pyvispoly-0.3.1.dist-info/RECORD
pyvispoly-0.3.1.dist-info/top_level.txt
pyvispoly-0.3.1.dist-info/METADATA
pyvispoly-0.3.1.dist-info/licenses/LICENSE
pyvispoly/__init__.py
pyvispoly/_cgal_bindings.cpython-311-i386-linux-gnu.so
pyvispoly/plotting.py
