Metadata-Version: 2.4
Name: pyvispoly
Version: 0.3.1
Summary: CGAL's visibility polygons in Python
Author: Dominik Krupke
License: LICENSE
Requires-Python: >=3.8
License-File: LICENSE
Requires-Dist: matplotlib>=3.4.2
Dynamic: author
Dynamic: description
Dynamic: description-content-type
Dynamic: license
Dynamic: license-file
Dynamic: requires-dist
Dynamic: requires-python
Dynamic: summary
